asyncio_mqtt/__init__.py
asyncio_mqtt/_version.py
asyncio_mqtt/client.py
asyncio_mqtt/error.py
asyncio_mqtt/py.typed
asyncio_mqtt/types.py
asyncio_mqtt-0.16.1.dist-info/LICENSE
asyncio_mqtt-0.16.1.dist-info/METADATA
asyncio_mqtt-0.16.1.dist-info/WHEEL
asyncio_mqtt-0.16.1.dist-info/top_level.txt
asyncio_mqtt-0.16.1.dist-info/RECORD
