Metadata-Version: 2.1
Name: asyncio_mqtt
Version: 0.16.1
Summary: Idiomatic asyncio wrapper around paho-mqtt
Author-email: Frederik Aalund <fpa@sbtinstruments.com>
Maintainer-email: Jonathan Plasse <jonathan.plasse@live.fr>, Felix Böhm <felix@felixboehm.dev>
License: BSD 3-Clause License
Project-URL: Source code, https://github.com/sbtinstruments/asyncio-mqtt
Project-URL: Issue tracker, https://github.com/sbtinstruments/asyncio-mqtt/issues
Keywords: mqtt,async,asyncio,paho-mqtt,wrapper
Classifier: Development Status :: 3 - Alpha
Classifier: Intended Audience :: Developers
Classifier: License :: OSI Approved
Classifier: Operating System :: POSIX :: Linux
Classifier: Operating System :: Microsoft :: Windows
Classifier: Operating System :: MacOS
Classifier: Programming Language :: Python :: 3
Classifier: Programming Language :: Python :: 3.7
Classifier: Programming Language :: Python :: 3.8
Classifier: Programming Language :: Python :: 3.9
Classifier: Programming Language :: Python :: 3.10
Classifier: Programming Language :: Python :: 3.11
Classifier: Programming Language :: Python :: Implementation :: CPython
Classifier: Programming Language :: Python :: Implementation :: PyPy
Requires-Python: >=3.7
Provides-Extra: lint
Provides-Extra: format
Provides-Extra: tests
License-File: LICENSE
